workspaceflow/__init__.py
workspaceflow/cache.py
workspaceflow/config.py
workspaceflow/exceptions.py
workspaceflow/setup.py
workspaceflow/api/__init__.py
workspaceflow/api/dependencies.py
workspaceflow/api/schemas.py
workspaceflow/api/workspace_routes.py
workspaceflow/core/__init__.py
workspaceflow/core/access_control.py
workspaceflow/core/middleware.py
workspaceflow/core/workspace.py
workspaceflow/models/base.py
workspaceflow/models/mixins.py
workspaceflow/models/workspace.py
workspaceflow/models/workspace_team.py
workspaceflow/utils/__init__.py
workspaceflow/utils/slug.py
workspaceflow-0.1.0.dist-info/METADATA
workspaceflow-0.1.0.dist-info/WHEEL
workspaceflow-0.1.0.dist-info/top_level.txt
workspaceflow-0.1.0.dist-info/RECORD
